{
	"id": "d4e05cba-4403-7026-b8b1-00f82b9e11d7",
	"name": "hotel",
	"description": "",
	"order": [
		"ce14c6b4-11c8-9cd4-6b73-e3fba455796c",
		"1e7949f4-985a-fdd9-6519-5d0e6cf1eaf3",
		"565fd67d-f24a-023d-179b-2c33add13cfd",
		"b68df7f0-caf3-c2fa-d20b-b942c86e23b1",
		"91b0e965-82f0-dc3e-e9ee-f437c0434363"
	],
	"folders": [],
	"folders_order": [],
	"timestamp": 1577017319393,
	"owner": 0,
	"public": false,
	"requests": [
		{
			"id": "1e7949f4-985a-fdd9-6519-5d0e6cf1eaf3",
			"headers": "Content-Type: application/json\n",
			"headerData": [
				{
					"key": "Content-Type",
					"value": "application/json",
					"description": "",
					"enabled": true
				}
			],
			"url": "localhost:3000/room/1/available",
			"queryParams": [],
			"pathVariables": {},
			"pathVariableData": [],
			"preRequestScript": null,
			"method": "POST",
			"collectionId": "d4e05cba-4403-7026-b8b1-00f82b9e11d7",
			"data": [],
			"dataMode": "raw",
			"name": "localhost:3000/room/1/available",
			"description": "",
			"descriptionFormat": "html",
			"time": 1577017348944,
			"version": 2,
			"responses": [],
			"tests": null,
			"currentHelper": "normal",
			"helperAttributes": {},
			"rawModeData": "{\n\t\"userId\":1,\n\t\"roomId\":1,\n\t\"checkIn\":1576315547,\n\t\"checkOut\":1576315547\n}"
		},
		{
			"id": "565fd67d-f24a-023d-179b-2c33add13cfd",
			"headers": "Content-Type: application/json\n",
			"headerData": [
				{
					"key": "Content-Type",
					"value": "application/json",
					"description": "",
					"enabled": true
				}
			],
			"url": "localhost:3000/booking",
			"queryParams": [],
			"pathVariables": {},
			"pathVariableData": [],
			"preRequestScript": null,
			"method": "POST",
			"collectionId": "d4e05cba-4403-7026-b8b1-00f82b9e11d7",
			"data": [],
			"dataMode": "raw",
			"name": "localhost:3000/booking",
			"description": "",
			"descriptionFormat": "html",
			"time": 1577017357464,
			"version": 2,
			"responses": [],
			"tests": null,
			"currentHelper": "normal",
			"helperAttributes": {},
			"rawModeData": "{\n\t\"userId\":1,\n\t\"roomId\":1,\n\t\"checkIn\":1575456411,\n\t\"checkOut\":1575542811\n}"
		},
		{
			"id": "91b0e965-82f0-dc3e-e9ee-f437c0434363",
			"headers": "",
			"headerData": [],
			"url": "localhost:3000/booking/1",
			"queryParams": [],
			"pathVariables": {},
			"pathVariableData": [],
			"preRequestScript": null,
			"method": "GET",
			"collectionId": "d4e05cba-4403-7026-b8b1-00f82b9e11d7",
			"data": null,
			"dataMode": "params",
			"name": "localhost:3000/booking/1",
			"description": "",
			"descriptionFormat": "html",
			"time": 1577019427401,
			"version": 2,
			"responses": [],
			"tests": null,
			"currentHelper": "normal",
			"helperAttributes": {}
		},
		{
			"id": "b68df7f0-caf3-c2fa-d20b-b942c86e23b1",
			"headers": "",
			"headerData": [],
			"url": "localhost:3000/room",
			"queryParams": [],
			"pathVariables": {},
			"pathVariableData": [],
			"preRequestScript": null,
			"method": "GET",
			"collectionId": "d4e05cba-4403-7026-b8b1-00f82b9e11d7",
			"data": null,
			"dataMode": "params",
			"name": "localhost:3000/room",
			"description": "",
			"descriptionFormat": "html",
			"time": 1577019386481,
			"version": 2,
			"responses": [],
			"tests": null,
			"currentHelper": "normal",
			"helperAttributes": {}
		},
		{
			"id": "ce14c6b4-11c8-9cd4-6b73-e3fba455796c",
			"headers": "",
			"headerData": [],
			"url": "localhost:3000/health",
			"queryParams": [],
			"pathVariables": {},
			"pathVariableData": [],
			"preRequestScript": null,
			"method": "GET",
			"collectionId": "d4e05cba-4403-7026-b8b1-00f82b9e11d7",
			"data": null,
			"dataMode": "params",
			"name": "localhost:3000/health",
			"description": "",
			"descriptionFormat": "html",
			"time": 1577017336728,
			"version": 2,
			"responses": [],
			"tests": null,
			"currentHelper": "normal",
			"helperAttributes": {}
		}
	]
}